pretty_help/__init__.py
pretty_help/menu.py
pretty_help/pretty_help.py
tests/__init__.py
tests/test_discord_pretty_help.py
tessa_pretty_help-0.0.5.dist-info/LICENSE
tessa_pretty_help-0.0.5.dist-info/METADATA
tessa_pretty_help-0.0.5.dist-info/WHEEL
tessa_pretty_help-0.0.5.dist-info/top_level.txt
tessa_pretty_help-0.0.5.dist-info/RECORD
