Metadata-Version: 2.1
Name: tessa-pretty-help
Version: 0.0.5
Summary: An embed version of the built in help command for discord.py and probably other forks of discord.py Inspired by the DefaultHelpCommand that discord.py uses, but revised for embeds and additional sorting on individual pages that can be scrolled through with reactions.. An improved version of discord-pretty-help
Home-page: https://github.com/prakarsh17/tessa-pretty-help
Author: Prakarsh17
Author-email: pranjal.prakarsh@outlook.com
License: UNKNOWN
Platform: UNKNOWN
Classifier: Programming Language :: Python :: 3
Classifier: License :: OSI Approved :: MIT License
Classifier: Operating System :: OS Independent
Requires-Python: >=3.6
